stirstick/__init__.py
stirstick/mixing.py
stirstick/plotting.py
stirstick-0.0.1.dist-info/LICENSE
stirstick-0.0.1.dist-info/METADATA
stirstick-0.0.1.dist-info/WHEEL
stirstick-0.0.1.dist-info/top_level.txt
stirstick-0.0.1.dist-info/RECORD
